[{
"Title": "Evaluations of disaster education programs for children",
"date": "Dec 10, 2015",
"tags": ["disaster","tornado","risk management"],
"division": "Health & Epidemics",
"Image":"",
"share":123
},
{
"Title": "UNISDR Annual Report 2014",
"date": "Dec 10, 2015",
"tags": ["disaster","tornado","risk management"],
"division": "Civil & Cyber Security",
"Image":"",
"share":123
},
{
"Title": "Mapping disaster risk: INFORM releases 2016 results",
"date": "Dec 10, 2015",
"tags": ["disaster","tornado","risk management"],
"division": "Business Continuity",
"Image":"",
"share":123
},
{
"Title": "John Constable",
"date": "Dec 10, 2015",
"tags": ["disaster","tornado","risk management"],
"division": "Business Continuity",
"Image":"",
"share":123
},
{
"Title": "John Constable",
"date": "Dec 10, 2015",
"tags": ["disaster","tornado","risk management"],
"division": "Health & Epidemics",
"Image":"",
"share":123
},
{
"Title": "International Day for the Elimination of Violence against Women",
"date": "Dec 10, 2015",
"tags": ["disaster","tornado","risk management"],
"division": "NGO Humanitarian",
"Image":"",
"share":123
},
{
"Title": "New paper on disaster risk research and assessment",
"date": "Dec 10, 2015",
"tags": ["disaster","tornado","risk management"],
"division": "NGO Humanitarian",
"Image":"",
"share":123
},
{
"Title": "Pan-Asia Risk Reduction (PARR) Fellowship Program",
"date": "Dec 10, 2015",
"tags": ["disaster","tornado","risk management"],
"division": "Science & Environment",
"Image":"",
"share":123
},
{
"Title": "John Constable",
"date": "Dec 10, 2015",
"tags": ["disaster","tornado","risk management"],
"division": "Science & Environment",
"Image":"",
"share":123
},
{
"Title": "European Commission to increase humanitarian ",
"date": "Dec 12, 2015",
"tags": ["disaster","tornado","risk management"],
"division": "Health & Epidemics",
"Image":"",
"share":123
}
]
